chchanges/__init__.py
chchanges/bayesian_online.py
chchanges/demos/__init__.py
chchanges/demos/mean.py
chchanges/demos/variance.py
chchanges/test/__init__.py
chchanges/test/test_bayesian_online.py
chchanges-1.0.4.dist-info/LICENSE
chchanges-1.0.4.dist-info/WHEEL
chchanges-1.0.4.dist-info/METADATA
chchanges-1.0.4.dist-info/RECORD
